listevery/__init__.py
listevery/__main__.py
listevery-0.1.4.dist-info/LICENSE
listevery-0.1.4.dist-info/METADATA
listevery-0.1.4.dist-info/WHEEL
listevery-0.1.4.dist-info/top_level.txt
listevery-0.1.4.dist-info/RECORD
