Metadata-Version: 2.1
Name: listevery
Version: 0.1.4
Summary: A file lister on steroids
Home-page: https://github.com/themysticsavages/listevery
Author: themysticsavages
Author-email: noemailprovidedthankyou@nonexistentemailservice.com
License: Apache
Platform: UNKNOWN
Classifier: Programming Language :: Python :: 3
Classifier: License :: OSI Approved :: MIT License
Classifier: Operating System :: OS Independent
Requires-Python: >=3.6
